[
    {
        "appointment_id": "29fmNrFZhVX9zW5tBZFNdbTzBZn2--8b33bed7-e8e2-40a5-9580-072b6e0cb63f",
        "business_id": "29fmNrFZhVX9zW5tBZFNdbTzBZn2",
        "customer_id": "fe3db288-6559-4c52-a786-bfc279649b34",
        "customer_name": "Troy Zimmerman",
        "service_id": "b77b593d-8d47-45d8-88c8-3bf8c9715771",
        "date": "2025-01-05",
        "time": "10:10:00",
        "number_of_customers": 2,
        "service_name": "tire rotation",
        "customer_phone_number": "(528)546-7163x441",
        "status": "waiting",
        "notes": "how awesome is this service and the staff, love it"
    },
    {
        "appointment_id": "29fmNrFZhVX9zW5tBZFNdbTzBZn2--27349f04-4f62-44bd-be94-706ba5d92933",
        "business_id": "29fmNrFZhVX9zW5tBZFNdbTzBZn2",
        "customer_id": "6929d563-0f41-439c-b8d5-1cfbf1368869",
        "customer_name": "Craig Riggs",
        "service_id": "b77b593d-8d47-45d8-88c8-3bf8c9715771",
        "date": "2025-02-24",
        "time": "17:55:00",
        "number_of_customers": 9,
        "service_name": "tire rotation",
        "customer_phone_number": "+1-611-551-9186x0575",
        "status": "completed",
        "notes": "how awesome is this service and the staff, love it"
    },
    {
        "appointment_id": "29fmNrFZhVX9zW5tBZFNdbTzBZn2--bd0a296f-6e49-485f-ab24-9cead97afb72",
        "business_id": "29fmNrFZhVX9zW5tBZFNdbTzBZn2",
        "customer_id": "b5e81aa6-39e1-4c4b-9e4b-aac10629b332",
        "customer_name": "Cassandra Brewer",
        "service_id": "b77b593d-8d47-45d8-88c8-3bf8c9715771",
        "date": "2025-02-14",
        "time": "13:25:00",
        "number_of_customers": 2,
        "service_name": "tire rotation",
        "customer_phone_number": "(717)713-9083x1068",
        "status": "completed",
        "notes": "how awesome is this service and the staff, love it"
    },
    {
        "appointment_id": "29fmNrFZhVX9zW5tBZFNdbTzBZn2--9fd4615e-0617-483a-ab1a-91600849c294",
        "business_id": "29fmNrFZhVX9zW5tBZFNdbTzBZn2",
        "customer_id": "695b3cb8-c4ad-4ffa-a4ce-c8d786f7f798",
        "customer_name": "Margaret Spencer",
        "service_id": "b77b593d-8d47-45d8-88c8-3bf8c9715771",
        "date": "2025-01-04",
        "time": "17:40:00",
        "number_of_customers": 1,
        "service_name": "tire rotation",
        "customer_phone_number": "231.588.7646x03969",
        "status": "completed",
        "notes": "how awesome is this service and the staff, love it"
    },
    {
        "appointment_id": "29fmNrFZhVX9zW5tBZFNdbTzBZn2--42a06b55-2e20-4005-a303-b41d6eff3477",
        "business_id": "29fmNrFZhVX9zW5tBZFNdbTzBZn2",
        "customer_id": "fe3db288-6559-4c52-a786-bfc279649b34",
        "customer_name": "Troy Zimmerman",
        "service_id": "b77b593d-8d47-45d8-88c8-3bf8c9715771",
        "date": "2025-02-12",
        "time": "09:20:00",
        "number_of_customers": 4,
        "service_name": "tire rotation",
        "customer_phone_number": "(528)546-7163x441",
        "status": "ongoing",
        "notes": "how awesome is this service and the staff, love it"
    },
    {
        "appointment_id": "29fmNrFZhVX9zW5tBZFNdbTzBZn2--7f7fb219-a727-49ca-a1c1-b383368a6b5d",
        "business_id": "29fmNrFZhVX9zW5tBZFNdbTzBZn2",
        "customer_id": "fe3db288-6559-4c52-a786-bfc279649b34",
        "customer_name": "Troy Zimmerman",
        "service_id": "b77b593d-8d47-45d8-88c8-3bf8c9715771",
        "date": "2025-02-06",
        "time": "12:20:00",
        "number_of_customers": 5,
        "service_name": "tire rotation",
        "customer_phone_number": "(528)546-7163x441",
        "status": "waiting",
        "notes": "how awesome is this service and the staff, love it"
    },
    {
        "appointment_id": "29fmNrFZhVX9zW5tBZFNdbTzBZn2--3ad9fd04-38c3-46c1-95a0-224d9a141343",
        "business_id": "29fmNrFZhVX9zW5tBZFNdbTzBZn2",
        "customer_id": "fe3db288-6559-4c52-a786-bfc279649b34",
        "customer_name": "Troy Zimmerman",
        "service_id": "d3dc58cf-63c8-48f5-b7fa-9ee705170092",
        "date": "2025-02-20",
        "time": "10:10:00",
        "number_of_customers": 4,
        "service_name": "oil change",
        "customer_phone_number": "(528)546-7163x441",
        "status": "waiting",
        "notes": "how awesome is this service and the staff, love it"
    },
    {
        "appointment_id": "29fmNrFZhVX9zW5tBZFNdbTzBZn2--f9d16fb0-604e-441f-8fce-3eb0c02c918d",
        "business_id": "29fmNrFZhVX9zW5tBZFNdbTzBZn2",
        "customer_id": "6929d563-0f41-439c-b8d5-1cfbf1368869",
        "customer_name": "Craig Riggs",
        "service_id": "b77b593d-8d47-45d8-88c8-3bf8c9715771",
        "date": "2025-01-24",
        "time": "14:25:00",
        "number_of_customers": 10,
        "service_name": "tire rotation",
        "customer_phone_number": "+1-611-551-9186x0575",
        "status": "completed",
        "notes": "how awesome is this service and the staff, love it"
    },
    {
        "appointment_id": "29fmNrFZhVX9zW5tBZFNdbTzBZn2--e9593e80-b858-437a-a60e-4014db13726a",
        "business_id": "29fmNrFZhVX9zW5tBZFNdbTzBZn2",
        "customer_id": "b5e81aa6-39e1-4c4b-9e4b-aac10629b332",
        "customer_name": "Cassandra Brewer",
        "service_id": "d3dc58cf-63c8-48f5-b7fa-9ee705170092",
        "date": "2025-02-03",
        "time": "09:20:00",
        "number_of_customers": 5,
        "service_name": "oil change",
        "customer_phone_number": "(717)713-9083x1068",
        "status": "ongoing",
        "notes": "how awesome is this service and the staff, love it"
    },
    {
        "appointment_id": "29fmNrFZhVX9zW5tBZFNdbTzBZn2--b9302b05-98d7-44fa-b543-87fdf6842081",
        "business_id": "29fmNrFZhVX9zW5tBZFNdbTzBZn2",
        "customer_id": "fe3db288-6559-4c52-a786-bfc279649b34",
        "customer_name": "Troy Zimmerman",
        "service_id": "d3dc58cf-63c8-48f5-b7fa-9ee705170092",
        "date": "2025-01-21",
        "time": "09:35:00",
        "number_of_customers": 10,
        "service_name": "oil change",
        "customer_phone_number": "(528)546-7163x441",
        "status": "ongoing",
        "notes": "how awesome is this service and the staff, love it"
    },
    {
        "appointment_id": "29fmNrFZhVX9zW5tBZFNdbTzBZn2--b8cf9577-6e8d-4f25-95e2-a2c13963c202",
        "business_id": "29fmNrFZhVX9zW5tBZFNdbTzBZn2",
        "customer_id": "695b3cb8-c4ad-4ffa-a4ce-c8d786f7f798",
        "customer_name": "Margaret Spencer",
        "service_id": "b77b593d-8d47-45d8-88c8-3bf8c9715771",
        "date": "2025-02-15",
        "time": "10:30:00",
        "number_of_customers": 6,
        "service_name": "tire rotation",
        "customer_phone_number": "231.588.7646x03969",
        "status": "waiting",
        "notes": "how awesome is this service and the staff, love it"
    },
    {
        "appointment_id": "29fmNrFZhVX9zW5tBZFNdbTzBZn2--67c2565a-8882-4bde-a26a-4dab9f5ce523",
        "business_id": "29fmNrFZhVX9zW5tBZFNdbTzBZn2",
        "customer_id": "e17f0935-cbc7-4e7b-bde8-ed93321c754a",
        "customer_name": "Erin Anderson",
        "service_id": "b77b593d-8d47-45d8-88c8-3bf8c9715771",
        "date": "2025-01-13",
        "time": "14:15:00",
        "number_of_customers": 9,
        "service_name": "tire rotation",
        "customer_phone_number": "787.888.7264x935",
        "status": "ongoing",
        "notes": "how awesome is this service and the staff, love it"
    },
    {
        "appointment_id": "29fmNrFZhVX9zW5tBZFNdbTzBZn2--1d7a43f0-02d0-4ffb-8478-a2f81d81cd79",
        "business_id": "29fmNrFZhVX9zW5tBZFNdbTzBZn2",
        "customer_id": "695b3cb8-c4ad-4ffa-a4ce-c8d786f7f798",
        "customer_name": "Margaret Spencer",
        "service_id": "b77b593d-8d47-45d8-88c8-3bf8c9715771",
        "date": "2025-02-07",
        "time": "10:50:00",
        "number_of_customers": 5,
        "service_name": "tire rotation",
        "customer_phone_number": "231.588.7646x03969",
        "status": "completed",
        "notes": "how awesome is this service and the staff, love it"
    },
    {
        "appointment_id": "29fmNrFZhVX9zW5tBZFNdbTzBZn2--02600b36-2c32-4e72-8955-95734c79a5c6",
        "business_id": "29fmNrFZhVX9zW5tBZFNdbTzBZn2",
        "customer_id": "695b3cb8-c4ad-4ffa-a4ce-c8d786f7f798",
        "customer_name": "Margaret Spencer",
        "service_id": "d3dc58cf-63c8-48f5-b7fa-9ee705170092",
        "date": "2025-01-14",
        "time": "11:15:00",
        "number_of_customers": 1,
        "service_name": "oil change",
        "customer_phone_number": "231.588.7646x03969",
        "status": "completed",
        "notes": "how awesome is this service and the staff, love it"
    },
    {
        "appointment_id": "29fmNrFZhVX9zW5tBZFNdbTzBZn2--9c863ceb-3b57-4497-93c6-585cd35095d5",
        "business_id": "29fmNrFZhVX9zW5tBZFNdbTzBZn2",
        "customer_id": "fe3db288-6559-4c52-a786-bfc279649b34",
        "customer_name": "Troy Zimmerman",
        "service_id": "d3dc58cf-63c8-48f5-b7fa-9ee705170092",
        "date": "2025-01-20",
        "time": "17:50:00",
        "number_of_customers": 6,
        "service_name": "oil change",
        "customer_phone_number": "(528)546-7163x441",
        "status": "completed",
        "notes": "how awesome is this service and the staff, love it"
    },
    {
        "appointment_id": "29fmNrFZhVX9zW5tBZFNdbTzBZn2--e8248cba-7f98-4c35-aedd-ec69b849d12b",
        "business_id": "29fmNrFZhVX9zW5tBZFNdbTzBZn2",
        "customer_id": "e17f0935-cbc7-4e7b-bde8-ed93321c754a",
        "customer_name": "Erin Anderson",
        "service_id": "b77b593d-8d47-45d8-88c8-3bf8c9715771",
        "date": "2025-02-12",
        "time": "11:05:00",
        "number_of_customers": 5,
        "service_name": "tire rotation",
        "customer_phone_number": "787.888.7264x935",
        "status": "ongoing",
        "notes": "how awesome is this service and the staff, love it"
    },
    {
        "appointment_id": "29fmNrFZhVX9zW5tBZFNdbTzBZn2--fc920e1f-6978-44cc-95d0-3afd9bad404d",
        "business_id": "29fmNrFZhVX9zW5tBZFNdbTzBZn2",
        "customer_id": "695b3cb8-c4ad-4ffa-a4ce-c8d786f7f798",
        "customer_name": "Margaret Spencer",
        "service_id": "b77b593d-8d47-45d8-88c8-3bf8c9715771",
        "date": "2025-01-17",
        "time": "14:30:00",
        "number_of_customers": 3,
        "service_name": "tire rotation",
        "customer_phone_number": "231.588.7646x03969",
        "status": "completed",
        "notes": "how awesome is this service and the staff, love it"
    },
    {
        "appointment_id": "29fmNrFZhVX9zW5tBZFNdbTzBZn2--7679b634-bd27-4b95-a152-a0bcf32ab3d3",
        "business_id": "29fmNrFZhVX9zW5tBZFNdbTzBZn2",
        "customer_id": "b5e81aa6-39e1-4c4b-9e4b-aac10629b332",
        "customer_name": "Cassandra Brewer",
        "service_id": "d3dc58cf-63c8-48f5-b7fa-9ee705170092",
        "date": "2025-01-09",
        "time": "15:40:00",
        "number_of_customers": 2,
        "service_name": "oil change",
        "customer_phone_number": "(717)713-9083x1068",
        "status": "ongoing",
        "notes": "how awesome is this service and the staff, love it"
    },
    {
        "appointment_id": "29fmNrFZhVX9zW5tBZFNdbTzBZn2--de1aeda5-c8e4-4e28-8698-6e20c08d644f",
        "business_id": "29fmNrFZhVX9zW5tBZFNdbTzBZn2",
        "customer_id": "e17f0935-cbc7-4e7b-bde8-ed93321c754a",
        "customer_name": "Erin Anderson",
        "service_id": "b77b593d-8d47-45d8-88c8-3bf8c9715771",
        "date": "2025-02-13",
        "time": "14:25:00",
        "number_of_customers": 9,
        "service_name": "tire rotation",
        "customer_phone_number": "787.888.7264x935",
        "status": "ongoing",
        "notes": "how awesome is this service and the staff, love it"
    },
    {
        "appointment_id": "Lxt6LjxXa9acMDqeHdbuodstNim1--bffe27dc-0ea7-4853-9640-99e7a5d07812",
        "business_id": "Lxt6LjxXa9acMDqeHdbuodstNim1",
        "customer_id": "6929d563-0f41-439c-b8d5-1cfbf1368869",
        "customer_name": "Craig Riggs",
        "service_id": "b77b593d-8d47-45d8-88c8-3bf8c9715771",
        "date": "2025-02-16",
        "time": "09:10:00",
        "number_of_customers": 10,
        "service_name": "tire rotation",
        "customer_phone_number": "+1-611-551-9186x0575",
        "status": "ongoing",
        "notes": "how awesome is this service and the staff, love it"
    },
    {
        "appointment_id": "Lxt6LjxXa9acMDqeHdbuodstNim1--46f33642-ea9d-458f-bf93-bbbdf2ad535e",
        "business_id": "Lxt6LjxXa9acMDqeHdbuodstNim1",
        "customer_id": "695b3cb8-c4ad-4ffa-a4ce-c8d786f7f798",
        "customer_name": "Margaret Spencer",
        "service_id": "b77b593d-8d47-45d8-88c8-3bf8c9715771",
        "date": "2025-02-07",
        "time": "12:30:00",
        "number_of_customers": 9,
        "service_name": "tire rotation",
        "customer_phone_number": "231.588.7646x03969",
        "status": "waiting",
        "notes": "how awesome is this service and the staff, love it"
    },
    {
        "appointment_id": "Lxt6LjxXa9acMDqeHdbuodstNim1--5b218b88-a448-48d6-b868-cb38434bb3e7",
        "business_id": "Lxt6LjxXa9acMDqeHdbuodstNim1",
        "customer_id": "695b3cb8-c4ad-4ffa-a4ce-c8d786f7f798",
        "customer_name": "Margaret Spencer",
        "service_id": "b77b593d-8d47-45d8-88c8-3bf8c9715771",
        "date": "2025-02-14",
        "time": "14:35:00",
        "number_of_customers": 3,
        "service_name": "tire rotation",
        "customer_phone_number": "231.588.7646x03969",
        "status": "completed",
        "notes": "how awesome is this service and the staff, love it"
    },
    {
        "appointment_id": "Lxt6LjxXa9acMDqeHdbuodstNim1--aa4db653-7069-4b0f-b03c-7b9291345b83",
        "business_id": "Lxt6LjxXa9acMDqeHdbuodstNim1",
        "customer_id": "e17f0935-cbc7-4e7b-bde8-ed93321c754a",
        "customer_name": "Erin Anderson",
        "service_id": "d3dc58cf-63c8-48f5-b7fa-9ee705170092",
        "date": "2025-01-08",
        "time": "15:50:00",
        "number_of_customers": 10,
        "service_name": "oil change",
        "customer_phone_number": "787.888.7264x935",
        "status": "completed",
        "notes": "how awesome is this service and the staff, love it"
    },
    {
        "appointment_id": "Lxt6LjxXa9acMDqeHdbuodstNim1--f48cdc1e-3c2a-4a6f-befe-3bd14e0c5ba6",
        "business_id": "Lxt6LjxXa9acMDqeHdbuodstNim1",
        "customer_id": "6929d563-0f41-439c-b8d5-1cfbf1368869",
        "customer_name": "Craig Riggs",
        "service_id": "d3dc58cf-63c8-48f5-b7fa-9ee705170092",
        "date": "2025-01-13",
        "time": "09:40:00",
        "number_of_customers": 1,
        "service_name": "oil change",
        "customer_phone_number": "+1-611-551-9186x0575",
        "status": "completed",
        "notes": "how awesome is this service and the staff, love it"
    },
    {
        "appointment_id": "Lxt6LjxXa9acMDqeHdbuodstNim1--28760650-37d0-446b-a755-f91a906ce8b2",
        "business_id": "Lxt6LjxXa9acMDqeHdbuodstNim1",
        "customer_id": "6929d563-0f41-439c-b8d5-1cfbf1368869",
        "customer_name": "Craig Riggs",
        "service_id": "d3dc58cf-63c8-48f5-b7fa-9ee705170092",
        "date": "2025-02-09",
        "time": "10:15:00",
        "number_of_customers": 6,
        "service_name": "oil change",
        "customer_phone_number": "+1-611-551-9186x0575",
        "status": "waiting",
        "notes": "how awesome is this service and the staff, love it"
    },
    {
        "appointment_id": "Lxt6LjxXa9acMDqeHdbuodstNim1--ba36e8cf-15c8-4f86-87e8-907a72150a17",
        "business_id": "Lxt6LjxXa9acMDqeHdbuodstNim1",
        "customer_id": "fe3db288-6559-4c52-a786-bfc279649b34",
        "customer_name": "Troy Zimmerman",
        "service_id": "d3dc58cf-63c8-48f5-b7fa-9ee705170092",
        "date": "2025-01-20",
        "time": "16:10:00",
        "number_of_customers": 6,
        "service_name": "oil change",
        "customer_phone_number": "(528)546-7163x441",
        "status": "waiting",
        "notes": "how awesome is this service and the staff, love it"
    },
    {
        "appointment_id": "Lxt6LjxXa9acMDqeHdbuodstNim1--0bb9ff51-3d03-495b-ac84-c9854f5d46cc",
        "business_id": "Lxt6LjxXa9acMDqeHdbuodstNim1",
        "customer_id": "b5e81aa6-39e1-4c4b-9e4b-aac10629b332",
        "customer_name": "Cassandra Brewer",
        "service_id": "d3dc58cf-63c8-48f5-b7fa-9ee705170092",
        "date": "2025-01-28",
        "time": "09:45:00",
        "number_of_customers": 6,
        "service_name": "oil change",
        "customer_phone_number": "(717)713-9083x1068",
        "status": "completed",
        "notes": "how awesome is this service and the staff, love it"
    },
    {
        "appointment_id": "Lxt6LjxXa9acMDqeHdbuodstNim1--299eb471-a768-4065-af82-4a2caf1e9359",
        "business_id": "Lxt6LjxXa9acMDqeHdbuodstNim1",
        "customer_id": "b5e81aa6-39e1-4c4b-9e4b-aac10629b332",
        "customer_name": "Cassandra Brewer",
        "service_id": "d3dc58cf-63c8-48f5-b7fa-9ee705170092",
        "date": "2025-02-05",
        "time": "11:55:00",
        "number_of_customers": 1,
        "service_name": "oil change",
        "customer_phone_number": "(717)713-9083x1068",
        "status": "ongoing",
        "notes": "how awesome is this service and the staff, love it"
    },
    {
        "appointment_id": "Lxt6LjxXa9acMDqeHdbuodstNim1--f02ebc12-d1ea-42d4-ad36-eaf477094d64",
        "business_id": "Lxt6LjxXa9acMDqeHdbuodstNim1",
        "customer_id": "b5e81aa6-39e1-4c4b-9e4b-aac10629b332",
        "customer_name": "Cassandra Brewer",
        "service_id": "d3dc58cf-63c8-48f5-b7fa-9ee705170092",
        "date": "2025-01-30",
        "time": "11:25:00",
        "number_of_customers": 4,
        "service_name": "oil change",
        "customer_phone_number": "(717)713-9083x1068",
        "status": "waiting",
        "notes": "how awesome is this service and the staff, love it"
    },
    {
        "appointment_id": "Lxt6LjxXa9acMDqeHdbuodstNim1--6d33e3af-0296-4268-a962-e6ab18350978",
        "business_id": "Lxt6LjxXa9acMDqeHdbuodstNim1",
        "customer_id": "b5e81aa6-39e1-4c4b-9e4b-aac10629b332",
        "customer_name": "Cassandra Brewer",
        "service_id": "d3dc58cf-63c8-48f5-b7fa-9ee705170092",
        "date": "2025-01-22",
        "time": "13:45:00",
        "number_of_customers": 2,
        "service_name": "oil change",
        "customer_phone_number": "(717)713-9083x1068",
        "status": "ongoing",
        "notes": "how awesome is this service and the staff, love it"
    },
    {
        "appointment_id": "Lxt6LjxXa9acMDqeHdbuodstNim1--3b2c5e04-0fce-449e-8f07-2df6a48d36bb",
        "business_id": "Lxt6LjxXa9acMDqeHdbuodstNim1",
        "customer_id": "fe3db288-6559-4c52-a786-bfc279649b34",
        "customer_name": "Troy Zimmerman",
        "service_id": "d3dc58cf-63c8-48f5-b7fa-9ee705170092",
        "date": "2025-01-08",
        "time": "10:05:00",
        "number_of_customers": 9,
        "service_name": "oil change",
        "customer_phone_number": "(528)546-7163x441",
        "status": "waiting",
        "notes": "how awesome is this service and the staff, love it"
    },
    {
        "appointment_id": "Lxt6LjxXa9acMDqeHdbuodstNim1--229c9007-ba91-4617-84b4-be74fb032598",
        "business_id": "Lxt6LjxXa9acMDqeHdbuodstNim1",
        "customer_id": "b5e81aa6-39e1-4c4b-9e4b-aac10629b332",
        "customer_name": "Cassandra Brewer",
        "service_id": "b77b593d-8d47-45d8-88c8-3bf8c9715771",
        "date": "2025-02-09",
        "time": "12:15:00",
        "number_of_customers": 10,
        "service_name": "tire rotation",
        "customer_phone_number": "(717)713-9083x1068",
        "status": "completed",
        "notes": "how awesome is this service and the staff, love it"
    },
    {
        "appointment_id": "Lxt6LjxXa9acMDqeHdbuodstNim1--7bd8735d-1f6c-48fb-baae-3928ee92c15a",
        "business_id": "Lxt6LjxXa9acMDqeHdbuodstNim1",
        "customer_id": "6929d563-0f41-439c-b8d5-1cfbf1368869",
        "customer_name": "Craig Riggs",
        "service_id": "d3dc58cf-63c8-48f5-b7fa-9ee705170092",
        "date": "2025-01-18",
        "time": "14:35:00",
        "number_of_customers": 2,
        "service_name": "oil change",
        "customer_phone_number": "+1-611-551-9186x0575",
        "status": "ongoing",
        "notes": "how awesome is this service and the staff, love it"
    }
]